<annotation>
	<folder>images</folder>
	<filename>0693a49bad451a49.jpg</filename>
	<source>
		<database>Unknown</database>
	</source>
	<size>
		<width>1024</width>
		<height>522</height>
		<depth>3</depth>
	</size>
	<segmented>0</segmented>
	<object>
		<name>licence</name>
		<pose>Unspecified</pose>
		<truncated>0</truncated>
		<difficult>0</difficult>
		<bndbox>
			<xmin>148</xmin>
			<ymin>302</ymin>
			<xmax>194</xmax>
			<ymax>316</ymax>
		</bndbox>
	</object>
	<object>
		<name>licence</name>
		<pose>Unspecified</pose>
		<truncated>0</truncated>
		<difficult>0</difficult>
		<bndbox>
			<xmin>446</xmin>
			<ymin>304</ymin>
			<xmax>495</xmax>
			<ymax>321</ymax>
		</bndbox>
	</object>
</annotation>
