<annotation>
	<folder>images</folder>
	<filename>9e9aeeb474ac10cf.jpg</filename>
	<source>
		<database>Unknown</database>
	</source>
	<size>
		<width>1024</width>
		<height>503</height>
		<depth>3</depth>
	</size>
	<segmented>0</segmented>
	<object>
		<name>licence</name>
		<pose>Unspecified</pose>
		<truncated>0</truncated>
		<difficult>0</difficult>
		<bndbox>
			<xmin>140</xmin>
			<ymin>234</ymin>
			<xmax>268</xmax>
			<ymax>280</ymax>
		</bndbox>
	</object>
	<object>
		<name>licence</name>
		<pose>Unspecified</pose>
		<truncated>0</truncated>
		<difficult>0</difficult>
		<bndbox>
			<xmin>863</xmin>
			<ymin>164</ymin>
			<xmax>934</xmax>
			<ymax>189</ymax>
		</bndbox>
	</object>
</annotation>
