<annotation>
	<folder>images</folder>
	<filename>ce9c87cb1933e30b.jpg</filename>
	<source>
		<database>Unknown</database>
	</source>
	<size>
		<width>1024</width>
		<height>768</height>
		<depth>3</depth>
	</size>
	<segmented>0</segmented>
	<object>
		<name>licence</name>
		<pose>Unspecified</pose>
		<truncated>0</truncated>
		<difficult>0</difficult>
		<bndbox>
			<xmin>0</xmin>
			<ymin>710</ymin>
			<xmax>38</xmax>
			<ymax>738</ymax>
		</bndbox>
	</object>
	<object>
		<name>licence</name>
		<pose>Unspecified</pose>
		<truncated>0</truncated>
		<difficult>0</difficult>
		<bndbox>
			<xmin>895</xmin>
			<ymin>653</ymin>
			<xmax>940</xmax>
			<ymax>664</ymax>
		</bndbox>
	</object>
</annotation>
